README.md
setup.py
opLang/__init__.py
operator_language.egg-info/PKG-INFO
operator_language.egg-info/SOURCES.txt
operator_language.egg-info/dependency_links.txt
operator_language.egg-info/entry_points.txt
operator_language.egg-info/top_level.txt