Metadata-Version: 2.1
Name: operator-language
Version: 0.0.5
Summary: 自制解释性语言
Home-page: https://github.com/
Author: Jianrui Li
Author-email: lijianrui7560@qq.com
Classifier: Programming Language :: Python :: 3
Classifier: License :: OSI Approved :: MIT License
Classifier: Operating System :: OS Independent
